README.rst
setup.py
obj2xml/__init__.py
obj2xml.egg-info/PKG-INFO
obj2xml.egg-info/SOURCES.txt
obj2xml.egg-info/dependency_links.txt
obj2xml.egg-info/requires.txt
obj2xml.egg-info/top_level.txt