Metadata-Version: 1.1
Name: obj2xml
Version: 1.0.1
Summary: Convenient XML creation using objects
Home-page: https://github.com/adamlwgriffiths/obj2xml
Author: Adam Griffiths
Author-email: adam.lw.griffiths@gmail.com
License: BSD
Platform: any
Classifier: Natural Language :: English
Classifier: Intended Audience :: Developers
Classifier: Operating System :: MacOS :: MacOS X
Classifier: Operating System :: Microsoft :: Windows
Classifier: Operating System :: POSIX
Classifier: Programming Language :: Python
Classifier: License :: OSI Approved :: BSD License
Classifier: Topic :: Software Development :: Libraries
Classifier: Topic :: Software Development :: Libraries :: Python Modules
Classifier: Topic :: Text Processing :: Markup :: XML
